fdi/__init__.py
fdi/_version.py
fdi/dataset/__init__.py
fdi/dataset/abstractcomposite.py
fdi/dataset/annotatable.py
fdi/dataset/arraydataset.py
fdi/dataset/arraydataset_datamodel.py
fdi/dataset/attributable.py
fdi/dataset/baseproduct.py
fdi/dataset/browseproduct.py
fdi/dataset/classes.py
fdi/dataset/collectionsMockUp.py
fdi/dataset/composite.py
fdi/dataset/copyable.py
fdi/dataset/dataset.py
fdi/dataset/datatypes.py
fdi/dataset/datawrapper.py
fdi/dataset/dateparameter.py
fdi/dataset/deserialize.py
fdi/dataset/eq.py
fdi/dataset/finetime.py
fdi/dataset/history.py
fdi/dataset/indexed.py
fdi/dataset/invalid.py
fdi/dataset/listener.py
fdi/dataset/mediawrapper.py
fdi/dataset/mediawrapper_datamodel.py
fdi/dataset/messagequeue.py
fdi/dataset/metadata.py
fdi/dataset/metadataholder.py
fdi/dataset/namespace.py
fdi/dataset/ndprint.py
fdi/dataset/numericparameter.py
fdi/dataset/odict.py
fdi/dataset/product.py
fdi/dataset/quantifiable.py
fdi/dataset/readonlydict.py
fdi/dataset/schemas.py
fdi/dataset/serializable.py
fdi/dataset/shaped.py
fdi/dataset/stringparameter.py
fdi/dataset/tabledataset.py
fdi/dataset/tabledataset_datamodel.py
fdi/dataset/testproducts.py
fdi/dataset/typecoded.py
fdi/dataset/typed.py
fdi/dataset/unstructureddataset.py
fdi/dataset/unstructureddataset_datamodel.py
fdi/dataset/yaml2python.py
fdi/dataset/resources/ArrayDataset_DataModel.template
fdi/dataset/resources/ArrayDataset_DataModel.yml
fdi/dataset/resources/BaseProduct.rst
fdi/dataset/resources/BaseProduct.template
fdi/dataset/resources/BaseProduct.txt
fdi/dataset/resources/BaseProduct.yml
fdi/dataset/resources/BrowseProduct.txt
fdi/dataset/resources/BrowseProduct.yml
fdi/dataset/resources/Mandatory.csv
fdi/dataset/resources/Mandatory.json
fdi/dataset/resources/Mandatory.yml_
fdi/dataset/resources/Mandatory_corr.json
fdi/dataset/resources/MediaWrapper_DataModel.template
fdi/dataset/resources/MediaWrapper_DataModel.yml
fdi/dataset/resources/Product.rst
fdi/dataset/resources/Product.template
fdi-1.34.2.dist-info/LICENSE
fdi-1.34.2.dist-info/METADATA
fdi-1.34.2.dist-info/WHEEL
fdi-1.34.2.dist-info/entry_points.txt
fdi-1.34.2.dist-info/top_level.txt
fdi-1.34.2.dist-info/RECORD
