Metadata-Version: 2.1
Name: fdi
Version: 1.34.2
Summary: Flexible Data Integrator
Home-page: http://mercury.bao.ac.cn:9006/mh/fdi
Author: Maohai Huang
Author-email: mhuang@earth.bao.ac.cn
License: LGPL v3
Keywords: dataset metadata processing product context serialization server URN RESTful API HCSS
Classifier: Development Status :: 4 - Beta
Classifier: Programming Language :: Python :: 3.8
Classifier: Topic :: Scientific/Engineering
Classifier: Topic :: Software Development :: Libraries :: Application Frameworks
Classifier: Topic :: Software Development :: Libraries :: Python Modules
Classifier: Topic :: Utilities
Classifier: Framework :: Flask
Classifier: Framework :: Pytest
Classifier: Intended Audience :: Science/Research
Classifier: License :: OSI Approved :: GNU Lesser General Public License v3 (LGPLv3)
Requires-Python: >=3.8
License-File: LICENSE
Requires-Dist: requests (>=2.23.0)
Requires-Dist: filelock (>=3.10)
Requires-Dist: ruamel.yaml (<0.17)
Requires-Dist: tabulate-expwidth (>=0.9.0.1)
Requires-Dist: cwcwidth (>=0.1.5)
Requires-Dist: paho-mqtt (>=1.6.1)
Requires-Dist: jsonschema (>=3.2.0)
Requires-Dist: xmltodict (>=0.12.0)
Requires-Dist: jsonpath-ng (>=1.5.3)
Requires-Dist: pypng
Requires-Dist: networkx (>=2.8.1)
Requires-Dist: pydot (>=1.4.2)
Requires-Dist: importlib-resources (>=5.12.0)
Provides-Extra: dev
Requires-Dist: setuptools (>=43.0.0) ; extra == 'dev'
Requires-Dist: wheel (>=0.32.1) ; extra == 'dev'
Requires-Dist: pytest (>=5.4.1) ; extra == 'dev'
Requires-Dist: pytest-cov ; extra == 'dev'
Requires-Dist: remote-pdb ; extra == 'dev'
Provides-Extra: pub
Requires-Dist: sphinx (>=4.4.0) ; extra == 'pub'
Requires-Dist: sphinx-rtd-theme ; extra == 'pub'
Requires-Dist: alabaster (>=0.7.12) ; extra == 'pub'
Requires-Dist: sphinx-copybutton (>=0.3.0) ; extra == 'pub'
Requires-Dist: twine (>=3.3.0) ; extra == 'pub'
Provides-Extra: sci
Requires-Dist: astropy (>=5.2.1) ; extra == 'sci'
Provides-Extra: serv
Requires-Dist: requests (==2.28.1) ; extra == 'serv'
Requires-Dist: urllib3 (==1.26.13) ; extra == 'serv'
Requires-Dist: Flask-HTTPAuth (>=4.1.0) ; extra == 'serv'
Requires-Dist: Flask (<2.3) ; extra == 'serv'
Requires-Dist: Werkzeug[watchdog] ; extra == 'serv'
Requires-Dist: uwsgi (>=2.0.20) ; extra == 'serv'
Requires-Dist: flasgger (>=0.9.5) ; extra == 'serv'
Requires-Dist: aiohttp (>=3.8.3) ; extra == 'serv'
Requires-Dist: aiohttp-retry (>=2.8.3) ; extra == 'serv'
